setup.cfg
setup.py
django_render/__init__.py
django_render/annotations/__init__.py
django_render/annotations/url_refactor.py
django_render/middleware/__init__.py
django_render/middleware/multihost.py
django_render/url_patterns_maker/__init__.py
django_render/url_patterns_maker/url_patterns_maker.py
django_render_url.egg-info/PKG-INFO
django_render_url.egg-info/SOURCES.txt
django_render_url.egg-info/dependency_links.txt
django_render_url.egg-info/not-zip-safe
django_render_url.egg-info/pbr.json
django_render_url.egg-info/requires.txt
django_render_url.egg-info/top_level.txt