Metadata-Version: 1.1
Name: django-render-url
Version: 0.10
Summary: a very light django plugin
Home-page: https://github.com/wangtai/django_render
Author: WANG Tai
Author-email: i@wangtai.me
License: Apache2
Platform: UNKNOWN
Classifier: Development Status :: 4 - Beta
Classifier: Environment :: Web Environment
Classifier: Framework :: Django
Classifier: Intended Audience :: Developers
Classifier: Natural Language :: English
Classifier: Operating System :: POSIX :: Linux
Classifier: Programming Language :: Python
Classifier: Topic :: System :: Installation/Setup
